{"cameraMode":{"drawMode":0,"name":"Shaded","section":"Shading Mode"},"sceneLighting":true,"audioPlay":false,"sceneViewState":{"showFog":true,"showMaterialUpdate":false,"showSkybox":true,"showFlares":true,"showImageEffects":true,"showParticleSystems":true},"in2DMode":false,"pivot":{"x":48.93715286254883,"y":0.8019448518753052,"z":6.325449466705322},"rotation":{"x":0.3779480755329132,"y":-0.011391952633857727,"z":0.004650686401873827,"w":0.9257465600967407},"size":2.8578836917877199,"orthographic":false}